{
  "$schema": "http://json-schema.org/draft-07/schema#",
  "$id": "http://mapeo.world/schemas/project/v1.json",
  "title": "Project",
  "type": "object",
  "properties": {
    "schemaName": {
      "description": "Must be `project`",
      "type": "string",
      "const": "project"
    },
    "name": {
      "description": "name of the project",
      "type": "string"
    },
    "defaultPresets": {
      "type": "object",
      "properties": {
        "point": { "type": "array", "items":{"type":"string"}},
        "area": { "type": "array", "items":{"type":"string"}}
      }
    }
  },
  "required": ["schemaName", "name", "defaultPresets"],
  "additionalProperties": false
}
